kvasir/__init__.py
kvasir/distance.py
kvasir/gb_parse.py
kvasir/make_blast_db.py
kvasir/mongo_import.py
kvasir/output.py
kvasir/run.py
kvasir/run_blast.py
kvasirHGT-0.6.7.data/scripts/ani.rb
kvasirHGT-0.6.7.data/scripts/kv_analysis.py
kvasirHGT-0.6.7.data/scripts/kv_blast.py
kvasirHGT-0.6.7.data/scripts/kv_distance.py
kvasirHGT-0.6.7.data/scripts/kv_import.py
kvasirHGT-0.6.7.dist-info/DESCRIPTION.rst
kvasirHGT-0.6.7.dist-info/METADATA
kvasirHGT-0.6.7.dist-info/RECORD
kvasirHGT-0.6.7.dist-info/WHEEL
kvasirHGT-0.6.7.dist-info/metadata.json
kvasirHGT-0.6.7.dist-info/top_level.txt
tests/__init__.py
tests/basic_tests.py
