Metadata-Version: 2.0
Name: kvasirHGT
Version: 0.6.7
Summary: A package to identify HGT in bacterial genomes
Home-page: http://github.com/kescobo/kvasir
Author: Kevin Bonham, PhD
Author-email: kevbonham@gmail.com
License: MIT
Download-URL: https://github.com/kescobo/kvasir/archive/v0.6.7-beta.tar.gz
Keywords: HGT,biology,bacteria,genomics
Platform: UNKNOWN
Classifier: Development Status :: 4 - Beta
Classifier: Topic :: Scientific/Engineering :: Bio-Informatics
Classifier: License :: OSI Approved :: MIT License
